skywise_rest_client-1.0.2.dist-info/DESCRIPTION.rst
skywise_rest_client-1.0.2.dist-info/METADATA
skywise_rest_client-1.0.2.dist-info/metadata.json
skywise_rest_client-1.0.2.dist-info/RECORD
skywise_rest_client-1.0.2.dist-info/top_level.txt
skywise_rest_client-1.0.2.dist-info/WHEEL
skywiserestclient/__init__.py
skywiserestclient/exceptions.py
skywiserestclient/skywise.py
skywiserestclient/validation/__init__.py
