Metadata-Version: 2.0
Name: skywise-rest-client
Version: 1.0.2
Summary: SkyWise Rest Client
Home-page: UNKNOWN
Author: Weather Decision Technologies
Author-email: jstewart@wdtinc.com
License: UNKNOWN
Platform: UNKNOWN
Classifier: Development Status :: 3 - Alpha
Classifier: Intended Audience :: Developers
Classifier: Natural Language :: English
Classifier: Programming Language :: Python
Classifier: Programming Language :: Python :: 2.7
Requires-Dist: arrow (==0.7.0)
Requires-Dist: geojson (==1.3.1)
Requires-Dist: gevent (>=1.0.1)
Requires-Dist: grequests (==0.2.0)
Requires-Dist: nose (==1.3.7)
Requires-Dist: python-dateutil (==2.1)
Requires-Dist: requests (==2.9.1)
Requires-Dist: six (==1.10.0)
Requires-Dist: voluptuous (==0.8.8)
Requires-Dist: wheel (==0.24.0)
